colortext/__init__.py
colortext/colortext.py
simple_colortext-0.1.1.dist-info/licenses/LICENSE
simple_colortext-0.1.1.dist-info/METADATA
simple_colortext-0.1.1.dist-info/WHEEL
simple_colortext-0.1.1.dist-info/top_level.txt
simple_colortext-0.1.1.dist-info/RECORD
