Metadata-Version: 2.4
Name: simple-colortext
Version: 0.1.1
Summary: A simple package to print colored text in terminal
Home-page: https://github.com/ananydoneria/simple-colortext
Author: Anany Doneria
Author-email: ananydoneria47@gmail.com
Classifier: Programming Language :: Python :: 3
Classifier: License :: OSI Approved :: MIT License
Classifier: Operating System :: OS Independent
Requires-Python: >=3.6
License-File: LICENSE
Dynamic: author
Dynamic: author-email
Dynamic: classifier
Dynamic: description
Dynamic: description-content-type
Dynamic: home-page
Dynamic: license-file
Dynamic: requires-python
Dynamic: summary
